weaviate_datasets/__init__.py
weaviate_datasets/datasets.py
weaviate_datasets/data/_init_.py
weaviate_datasets/data/jeopardy_10k.json
weaviate_datasets/data/jeopardy_10k.json.npy
weaviate_datasets/data/jeopardy_10k_categories.csv
weaviate_datasets/data/jeopardy_1k.json
weaviate_datasets/data/jeopardy_1k.json.npy
weaviate_datasets/data/jeopardy_1k_categories.csv
weaviate_datasets/data/newsarticles_schema.json
weaviate_datasets/data/winemag_tiny.csv
weaviate_datasets/data/wiki100/Africa.txt
weaviate_datasets/data/wiki100/Agriculture.txt
weaviate_datasets/data/wiki100/Anatomy.txt
weaviate_datasets/data/wiki100/Ancient history.txt
weaviate_datasets/data/wiki100/Animal.txt
weaviate_datasets/data/wiki100/Architecture.txt
weaviate_datasets/data/wiki100/Arithmetic.txt
weaviate_datasets/data/wiki100/Asia.txt
weaviate_datasets/data/wiki100/Astronomy.txt
weaviate_datasets/data/wiki100/Atom.txt
weaviate_datasets/data/wiki100/Biology.txt
weaviate_datasets/data/wiki100/Book.txt
weaviate_datasets/data/wiki100/Business.txt
weaviate_datasets/data/wiki100/Cell (biology).txt
weaviate_datasets/data/wiki100/Chemical element.txt
weaviate_datasets/data/wiki100/Chemistry.txt
weaviate_datasets/data/wiki100/City.txt
weaviate_datasets/data/wiki100/Civilization.txt
weaviate_datasets/data/wiki100/Climate.txt
weaviate_datasets/data/wiki100/Clothing.txt
weaviate_datasets/data/wiki100/Communication.txt
weaviate_datasets/data/wiki100/Computer.txt
weaviate_datasets/data/wiki100/Country.txt
weaviate_datasets/data/wiki100/Culture.txt
weaviate_datasets/data/wiki100/Death.txt
weaviate_datasets/data/wiki100/Deity.txt
weaviate_datasets/data/wiki100/Disease.txt
weaviate_datasets/data/wiki100/Early modern period.txt
weaviate_datasets/data/wiki100/Earth.txt
weaviate_datasets/data/wiki100/Ecology.txt
weaviate_datasets/data/wiki100/Economics.txt
weaviate_datasets/data/wiki100/Education.txt
weaviate_datasets/data/wiki100/Electricity.txt
weaviate_datasets/data/wiki100/Emotion.txt
weaviate_demo_datasets-0.8.1.dist-info/METADATA
weaviate_demo_datasets-0.8.1.dist-info/WHEEL
weaviate_demo_datasets-0.8.1.dist-info/top_level.txt
weaviate_demo_datasets-0.8.1.dist-info/RECORD
