Metadata-Version: 2.4
Name: weaviate-demo-datasets
Version: 0.8.1
Summary: Unofficial demo datasets for Weaviate
Author-email: JP Hwang <me@jphwang.com>
Requires-Python: >=3.8
Requires-Dist: pandas
Requires-Dist: numpy
Requires-Dist: tqdm
